csvreader/__init__.py
csvreader/__main__.py
csvreader/csvreader.py
csvreader-0.0.4.dist-info/METADATA
csvreader-0.0.4.dist-info/WHEEL
csvreader-0.0.4.dist-info/top_level.txt
csvreader-0.0.4.dist-info/RECORD
