Metadata-Version: 1.0
Name: csvreader
Version: 0.0.4
Summary: A Library that Reads and Writes CSV Files Quickly.
Home-page: UNKNOWN
Author: SF Publishing
Author-email: UNKNOWN
License: UNKNOWN
Platform: UNKNOWN
